GWlal-0.0.2.dist-info/DESCRIPTION.rst
GWlal-0.0.2.dist-info/METADATA
GWlal-0.0.2.dist-info/RECORD
GWlal-0.0.2.dist-info/WHEEL
GWlal-0.0.2.dist-info/metadata.json
GWlal-0.0.2.dist-info/top_level.txt
GWlal-0.0.2.dist-info/zip-safe
lal/__init__.py
